trades.cpython-36m-x86_64-linux-gnu.so
pylob/level2.py
pylob/__init__.py
pylob/statistics.py
pylob/output.py
pylob/trades/trades.cpp
pylob/trades/bindings.cpp
pylob-0.2.8.dist-info/top_level.txt
pylob-0.2.8.dist-info/RECORD
pylob-0.2.8.dist-info/WHEEL
pylob-0.2.8.dist-info/METADATA
