Metadata-Version: 2.1
Name: pylob
Version: 0.2.8
Summary: Limit Order Book python module
Home-page: https://github.com/deltaleap/pylob
Author: Mattia Terenzi
Author-email: gammalightened@gmail.com
License: MIT
Platform: UNKNOWN
Classifier: License :: OSI Approved :: MIT License
Classifier: Programming Language :: Python :: 3
Classifier: Programming Language :: Python :: 3.6
Classifier: Programming Language :: Python :: 3.7
Classifier: Programming Language :: Python :: 3.8
Classifier: Programming Language :: Python :: 3.9
Classifier: Programming Language :: Python :: 3.10
